{
  "id": "a8ca1362-db13-4adf-8c58-78d39e2707ee",
  "prevId": "d5818833-f225-43e3-acad-1e7d4fd47bf0",
  "version": "7",
  "dialect": "postgresql",
  "tables": {
    "public.delegations": {
      "name": "delegations",
      "schema": "",
      "columns": {
        "id": {
          "name": "id",
          "type": "uuid",
          "primaryKey": true,
          "notNull": true
        },
        "user": {
          "name": "user",
          "type": "text",
          "primaryKey": false,
          "notNull": true
        },
        "delegationWalletPk": {
          "name": "delegationWalletPk",
          "type": "text",
          "primaryKey": false,
          "notNull": true
        },
        "createdAt": {
          "name": "createdAt",
          "type": "date",
          "primaryKey": false,
          "notNull": false,
          "default": "now()"
        }
      },
      "indexes": {},
      "foreignKeys": {
        "delegations_user_fk": {
          "name": "delegations_user_fk",
          "tableFrom": "delegations",
          "tableTo": "users",
          "columnsFrom": [
            "user"
          ],
          "columnsTo": [
            "wallet"
          ],
          "onDelete": "no action",
          "onUpdate": "no action"
        }
      },
      "compositePrimaryKeys": {},
      "uniqueConstraints": {},
      "policies": {},
      "checkConstraints": {},
      "isRLSEnabled": false
    },
    "public.strategy": {
      "name": "strategy",
      "schema": "",
      "columns": {
        "id": {
          "name": "id",
          "type": "uuid",
          "primaryKey": true,
          "notNull": true
        },
        "name": {
          "name": "name",
          "type": "text",
          "primaryKey": false,
          "notNull": true
        },
        "strategy": {
          "name": "strategy",
          "type": "text",
          "primaryKey": false,
          "notNull": true
        },
        "creatorWallet": {
          "name": "creatorWallet",
          "type": "text",
          "primaryKey": false,
          "notNull": false
        },
        "isActive": {
          "name": "isActive",
          "type": "boolean",
          "primaryKey": false,
          "notNull": false,
          "default": false
        },
        "isPublic": {
          "name": "isPublic",
          "type": "boolean",
          "primaryKey": false,
          "notNull": false,
          "default": false
        },
        "createdAt": {
          "name": "createdAt",
          "type": "date",
          "primaryKey": false,
          "notNull": false,
          "default": "now()"
        }
      },
      "indexes": {},
      "foreignKeys": {
        "strategy_creator_wallet_fk": {
          "name": "strategy_creator_wallet_fk",
          "tableFrom": "strategy",
          "tableTo": "users",
          "columnsFrom": [
            "creatorWallet"
          ],
          "columnsTo": [
            "wallet"
          ],
          "onDelete": "no action",
          "onUpdate": "no action"
        }
      },
      "compositePrimaryKeys": {},
      "uniqueConstraints": {},
      "policies": {},
      "checkConstraints": {},
      "isRLSEnabled": false
    },
    "public.strategy_subscriptions": {
      "name": "strategy_subscriptions",
      "schema": "",
      "columns": {
        "id": {
          "name": "id",
          "type": "uuid",
          "primaryKey": true,
          "notNull": true
        },
        "strategyId": {
          "name": "strategyId",
          "type": "uuid",
          "primaryKey": false,
          "notNull": true
        },
        "userWallet": {
          "name": "userWallet",
          "type": "text",
          "primaryKey": false,
          "notNull": true
        },
        "isActive": {
          "name": "isActive",
          "type": "boolean",
          "primaryKey": false,
          "notNull": false,
          "default": false
        },
        "createdAt": {
          "name": "createdAt",
          "type": "date",
          "primaryKey": false,
          "notNull": false,
          "default": "now()"
        }
      },
      "indexes": {},
      "foreignKeys": {
        "strategy_subscription_strategy_fk": {
          "name": "strategy_subscription_strategy_fk",
          "tableFrom": "strategy_subscriptions",
          "tableTo": "strategy",
          "columnsFrom": [
            "strategyId"
          ],
          "columnsTo": [
            "id"
          ],
          "onDelete": "no action",
          "onUpdate": "no action"
        },
        "strategy_subscription_user_fk": {
          "name": "strategy_subscription_user_fk",
          "tableFrom": "strategy_subscriptions",
          "tableTo": "users",
          "columnsFrom": [
            "userWallet"
          ],
          "columnsTo": [
            "wallet"
          ],
          "onDelete": "no action",
          "onUpdate": "no action"
        }
      },
      "compositePrimaryKeys": {},
      "uniqueConstraints": {},
      "policies": {},
      "checkConstraints": {},
      "isRLSEnabled": false
    },
    "public.subscription_wallets": {
      "name": "subscription_wallets",
      "schema": "",
      "columns": {
        "id": {
          "name": "id",
          "type": "uuid",
          "primaryKey": true,
          "notNull": true
        },
        "subscriptionId": {
          "name": "subscriptionId",
          "type": "uuid",
          "primaryKey": false,
          "notNull": true
        },
        "delegationWalletId": {
          "name": "delegationWalletId",
          "type": "uuid",
          "primaryKey": false,
          "notNull": true
        },
        "createdAt": {
          "name": "createdAt",
          "type": "date",
          "primaryKey": false,
          "notNull": false,
          "default": "now()"
        }
      },
      "indexes": {},
      "foreignKeys": {
        "subscription_wallet_subscription_fk": {
          "name": "subscription_wallet_subscription_fk",
          "tableFrom": "subscription_wallets",
          "tableTo": "strategy_subscriptions",
          "columnsFrom": [
            "subscriptionId"
          ],
          "columnsTo": [
            "id"
          ],
          "onDelete": "no action",
          "onUpdate": "no action"
        },
        "subscription_wallet_delegation_fk": {
          "name": "subscription_wallet_delegation_fk",
          "tableFrom": "subscription_wallets",
          "tableTo": "delegations",
          "columnsFrom": [
            "delegationWalletId"
          ],
          "columnsTo": [
            "id"
          ],
          "onDelete": "no action",
          "onUpdate": "no action"
        }
      },
      "compositePrimaryKeys": {},
      "uniqueConstraints": {},
      "policies": {},
      "checkConstraints": {},
      "isRLSEnabled": false
    },
    "public.users": {
      "name": "users",
      "schema": "",
      "columns": {
        "id": {
          "name": "id",
          "type": "uuid",
          "primaryKey": true,
          "notNull": true
        },
        "wallet": {
          "name": "wallet",
          "type": "text",
          "primaryKey": false,
          "notNull": true
        }
      },
      "indexes": {},
      "foreignKeys": {},
      "compositePrimaryKeys": {},
      "uniqueConstraints": {
        "users_wallet_unique": {
          "name": "users_wallet_unique",
          "nullsNotDistinct": false,
          "columns": [
            "wallet"
          ]
        }
      },
      "policies": {},
      "checkConstraints": {},
      "isRLSEnabled": false
    },
    "public.wallet_actions": {
      "name": "wallet_actions",
      "schema": "",
      "columns": {
        "id": {
          "name": "id",
          "type": "uuid",
          "primaryKey": true,
          "notNull": true
        },
        "action": {
          "name": "action",
          "type": "text",
          "primaryKey": false,
          "notNull": false
        },
        "strategy": {
          "name": "strategy",
          "type": "uuid",
          "primaryKey": false,
          "notNull": false
        },
        "userWallet": {
          "name": "userWallet",
          "type": "text",
          "primaryKey": false,
          "notNull": true
        },
        "delegationWalletId": {
          "name": "delegationWalletId",
          "type": "uuid",
          "primaryKey": false,
          "notNull": true
        },
        "subscriptionId": {
          "name": "subscriptionId",
          "type": "uuid",
          "primaryKey": false,
          "notNull": true
        },
        "stateChange": {
          "name": "stateChange",
          "type": "text",
          "primaryKey": false,
          "notNull": false
        },
        "createdAt": {
          "name": "createdAt",
          "type": "date",
          "primaryKey": false,
          "notNull": false,
          "default": "now()"
        }
      },
      "indexes": {},
      "foreignKeys": {
        "wallet_actions_strategy_fk": {
          "name": "wallet_actions_strategy_fk",
          "tableFrom": "wallet_actions",
          "tableTo": "strategy",
          "columnsFrom": [
            "strategy"
          ],
          "columnsTo": [
            "id"
          ],
          "onDelete": "no action",
          "onUpdate": "no action"
        },
        "wallet_actions_user_fk": {
          "name": "wallet_actions_user_fk",
          "tableFrom": "wallet_actions",
          "tableTo": "users",
          "columnsFrom": [
            "userWallet"
          ],
          "columnsTo": [
            "wallet"
          ],
          "onDelete": "no action",
          "onUpdate": "no action"
        },
        "wallet_actions_delegation_fk": {
          "name": "wallet_actions_delegation_fk",
          "tableFrom": "wallet_actions",
          "tableTo": "delegations",
          "columnsFrom": [
            "delegationWalletId"
          ],
          "columnsTo": [
            "id"
          ],
          "onDelete": "no action",
          "onUpdate": "no action"
        },
        "wallet_actions_subscription_fk": {
          "name": "wallet_actions_subscription_fk",
          "tableFrom": "wallet_actions",
          "tableTo": "strategy_subscriptions",
          "columnsFrom": [
            "subscriptionId"
          ],
          "columnsTo": [
            "id"
          ],
          "onDelete": "no action",
          "onUpdate": "no action"
        }
      },
      "compositePrimaryKeys": {},
      "uniqueConstraints": {},
      "policies": {},
      "checkConstraints": {},
      "isRLSEnabled": false
    }
  },
  "enums": {},
  "schemas": {},
  "sequences": {},
  "roles": {},
  "policies": {},
  "views": {},
  "_meta": {
    "columns": {},
    "schemas": {},
    "tables": {}
  }
}